{"hash":"acf4ad02dd6efa1a67de117afa33cc165e90ff11","data":{"tag":{"title":"Space Complexity","path":"/tag/space-complexity/","belongsTo":{"edges":[{"node":{"title":".NET Big-O Algorithm Complexity Cheat Sheet","date":"2015-10-15T00:00:00+00:00","dateModified":null,"timeToRead":1,"description":"Shows Big-O time and space complexities of common algorithms used in Computer Science and the.NET Framework to write the most efficient code.","path":"/net-big-o-algorithm-complexity-cheat-sheet/","published":true}}]}}},"context":{}}